pypkgs_ch/__init__.py
pypkgs_ch/pypkgs_ch.py
pypkgs_ch-0.1.0.dist-info/LICENSE
pypkgs_ch-0.1.0.dist-info/WHEEL
pypkgs_ch-0.1.0.dist-info/METADATA
pypkgs_ch-0.1.0.dist-info/RECORD
